{
  "benchmark": {
    "charts": {
      "find": "{\"caption\":\"Operations per second\",\"data\":[{\"colour\":\"#13aa52\",\"label\":\"mongodb\",\"value\":1905.4087837852996},{\"colour\":\"#e5a00d\",\"label\":\"papr\",\"value\":1916.317540072017},{\"colour\":\"#800\",\"label\":\"mongoose\",\"value\":1084.035623571724}],\"options\":{\"labels\":true},\"title\":\"Finds\",\"type\":\"review\"}",
      "insert": "{\"caption\":\"Operations per second\",\"data\":[{\"colour\":\"#13aa52\",\"label\":\"mongodb\",\"value\":2553.705544202324},{\"colour\":\"#e5a00d\",\"label\":\"papr\",\"value\":2528.273301085039},{\"colour\":\"#800\",\"label\":\"mongoose\",\"value\":1161.2352271384873}],\"options\":{\"labels\":true},\"title\":\"Inserts\",\"type\":\"review\"}",
      "update": "{\"caption\":\"Operations per second\",\"data\":[{\"colour\":\"#13aa52\",\"label\":\"mongodb\",\"value\":2730.828227393198},{\"colour\":\"#e5a00d\",\"label\":\"papr\",\"value\":2577.0857609330874},{\"colour\":\"#800\",\"label\":\"mongoose\",\"value\":2190.3824721459137}],\"options\":{\"labels\":true},\"title\":\"Updates\",\"type\":\"review\"}"
    },
    "configuration": "- node.js v20.11.0\n- mongodb v6.4.0\n- papr v15.2.1\n- mongoose v7.5.2\n- MongoDB server v6.0",
    "date": "May 15, 2024",
    "results": "mongodb.insert ~ 2553.71 ops/sec\npapr.insert ~ 2528.27 ops/sec\nmongoose.insert ~ 1161.24 ops/sec\n---\nmongodb.find ~ 1905.41 ops/sec\npapr.find ~ 1916.32 ops/sec\nmongoose.find ~ 1084.04 ops/sec\n---\nmongodb.update ~ 2730.83 ops/sec\npapr.update ~ 2577.09 ops/sec\nmongoose.update ~ 2190.38 ops/sec"
  }
}